.gitignore
protobom_py-0.1b1.dist-info/METADATA
protobom_py-0.1b1.dist-info/WHEEL
protobom_py-0.1b1.dist-info/licenses/LICENSE.txt
protobom_py/__init__.py
protobom_py/py.typed
protobom_py/sbom.proto
protobom_py/sbom_pb2.py
protobom_py/sbom_pb2.pyi
protobom_py/writer.wasm
protobom_py-0.1b1.dist-info/RECORD
