Metadata-Version: 2.1
Name: protobom-py
Version: 0.1b1
Author: Maximilian Hils
License:                                  Apache License
Project-URL: Source, https://github.com/appcensus-app-analysis/protobom-py
Requires-Python: >=3.10
Requires-Dist: protobuf
Requires-Dist: wasmtime
